adafruit_mlx90395.py
adafruit_circuitpython_mlx90395-1.0.18.dist-info/licenses/LICENSE
adafruit_circuitpython_mlx90395-1.0.18.dist-info/METADATA
adafruit_circuitpython_mlx90395-1.0.18.dist-info/WHEEL
adafruit_circuitpython_mlx90395-1.0.18.dist-info/top_level.txt
adafruit_circuitpython_mlx90395-1.0.18.dist-info/RECORD
