Metadata-Version: 2.4
Name: adafruit-circuitpython-mlx90395
Version: 1.0.18
Summary: CircuitPython helper library for using the Adafruit MLX90395 tri-Axis magnetometer breakout
Author-email: Adafruit Industries <circuitpython@adafruit.com>
License: MIT
Project-URL: Homepage, https://github.com/adafruit/Adafruit_CircuitPython_MLX90395
Keywords: adafruit,blinka,circuitpython,micropython,mlx90395,magnet,position,magnetometer,3-axis,hard,iron
Classifier: Intended Audience :: Developers
Classifier: Topic :: Software Development :: Libraries
Classifier: Topic :: Software Development :: Embedded Systems
Classifier: Topic :: System :: Hardware
Classifier: License :: OSI Approved :: MIT License
Classifier: Programming Language :: Python :: 3
License-File: LICENSE
Requires-Dist: Adafruit-Blinka
Requires-Dist: adafruit-circuitpython-register
Requires-Dist: adafruit-circuitpython-busdevice
Provides-Extra: optional
Dynamic: license-file
